mcompare/__init__.py
mcompare/classifiers_wrapper.py
mcompare/model_wrapper.py
mcompare/regressors_wrapper.py
mcompare_abditimer-0.0.1.dist-info/LICENSE
mcompare_abditimer-0.0.1.dist-info/METADATA
mcompare_abditimer-0.0.1.dist-info/WHEEL
mcompare_abditimer-0.0.1.dist-info/top_level.txt
mcompare_abditimer-0.0.1.dist-info/RECORD
