Metadata-Version: 2.1
Name: mcompare-abditimer
Version: 0.0.1
Summary: Wrapper for SKLearn Models
Home-page: https://github.com/pypa/sampleproject
Author: Abdi Timer
Author-email: thatimer@gmail.com
License: UNKNOWN
Platform: UNKNOWN
Classifier: Programming Language :: Python :: 3
Classifier: License :: OSI Approved :: MIT License
Classifier: Operating System :: OS Independent
Requires-Python: >=3.6
